CHANGES.txt
LICENSE.txt
MANIFEST.in
README.txt
setup.py
js/__init__.py
js.chai.egg-info/PKG-INFO
js.chai.egg-info/SOURCES.txt
js.chai.egg-info/dependency_links.txt
js.chai.egg-info/entry_points.txt
js.chai.egg-info/namespace_packages.txt
js.chai.egg-info/not-zip-safe
js.chai.egg-info/requires.txt
js.chai.egg-info/top_level.txt
js/chai/__init__.py
js/chai/test_chai.js.txt
js/chai/resources/chai.js