Metadata-Version: 1.0
Name: js.chai
Version: 3.2.0
Summary: Fanstatic packaging of chai.js
Home-page: UNKNOWN
Author: Fanstatic Developers
Author-email: fanstatic@googlegroups.com
License: BSD
Platform: UNKNOWN
